trame/__init__.py
trame/modules/__init__.py
trame/modules/matplotlib.py
trame/widgets/__init__.py
trame/widgets/matplotlib.py
trame_matplotlib/LICENSE
trame_matplotlib/__init__.py
trame_matplotlib/module/__init__.py
trame_matplotlib/module/serve/trame-matplotlib.umd.min.js
trame_matplotlib/widgets/__init__.py
trame_matplotlib/widgets/matplotlib.py
trame_matplotlib-2.0.3.dist-info/LICENSE
trame_matplotlib-2.0.3.dist-info/METADATA
trame_matplotlib-2.0.3.dist-info/WHEEL
trame_matplotlib-2.0.3.dist-info/top_level.txt
trame_matplotlib-2.0.3.dist-info/RECORD
